hfcf.py
PyHFCF-0.0.2.data/scripts/hfcf.py
PyHFCF-0.0.2.dist-info/METADATA
PyHFCF-0.0.2.dist-info/WHEEL
PyHFCF-0.0.2.dist-info/top_level.txt
PyHFCF-0.0.2.dist-info/RECORD
