Metadata-Version: 2.1
Name: PyHFCF
Version: 0.0.2
Home-page: https://github.com/DevHollo/pyhfcf
Author: Hollo
Author-email: hollo1234567890e@gmail.com
